[
    {
        "sentence": "When you die, you appear in a cinema with a number of other people who look like you. You find out that they are your previous reincarnations, and soon you all begin watching your next life on the big screen.",
        "source": "api",
        "start_progress": 0,
        "end_progress": 0.13454075032341525,
        "start_time": 0.0,
        "end_time": 0.0,
        "last_event_time": 631.0,
        "residual_vector": 0.0,
        "residual_vector_norm": 0
    },
    {
        "sentence": "When you die, you appear in a cinema with a number of other people who look like you. You find out that they are your previous reincarnations, and soon you all begin watching your next life on the big screen. This next life is the most amazing one yet! ",
        "source": "user",
        "start_progress": 0.13454075032341525,
        "end_progress": 0.16364812419146182,
        "start_time": 13.0,
        "end_time": 24.0,
        "last_event_time": 631.0,
        "residual_vector": 0.30303942140587536,
        "residual_vector_norm": 0.9257392691185077
    },
    {
        "sentence": "When you die, you appear in a cinema with a number of other people who look like you. You find out that they are your previous reincarnations, and soon you all begin watching your next life on the big screen. This next life is the most amazing one yet! You are rich, beautiful, and powerful.",
        "source": "api",
        "start_progress": 0.16364812419146182,
        "end_progress": 0.18822768434670117,
        "start_time": 59.0,
        "end_time": 59.0,
        "last_event_time": 631.0,
        "residual_vector": 0.27721681264062786,
        "residual_vector_norm": 0.9536964102346079
    },
    {
        "sentence": "When you die, you appear in a cinema with a number of other people who look like you. You find out that they are your previous reincarnations, and soon you all begin watching your next life on the big screen. This next life is the most amazing one yet! You are rich, beautiful, and powerful. You are confused about the presence of ",
        "source": "user",
        "start_progress": 0.18822768434670117,
        "end_progress": 0.21410090556274256,
        "start_time": 82.0,
        "end_time": 112.0,
        "last_event_time": 631.0,
        "residual_vector": 0.1703360724577239,
        "residual_vector_norm": 0.654346383467982
    },
    {
        "sentence": "When you die, you appear in a cinema with a number of other people who look like you. You find out that they are your previous reincarnations, and soon you all begin watching your next life on the big screen. This next life is the most amazing one yet! You are rich, beautiful, and powerful. You are confused about the presence of your previous selves, but file this question away as one of the more interesting philosophical problems you’ll explore in your next life.",
        "source": "api",
        "start_progress": 0.21410090556274256,
        "end_progress": 0.3027166882276843,
        "start_time": 128.0,
        "end_time": 128.0,
        "last_event_time": 631.0,
        "residual_vector": 0.24058836160224153,
        "residual_vector_norm": 0.25320388948367933
    },
    {
        "sentence": "When you die, you appear in a cinema with a number of other people who look like you. You find out that they are your previous reincarnations, and soon you all begin watching your next life on the big screen. This next life is the most amazing one yet! You are rich, beautiful, and powerful. You are confused about the presence of your previous selves, but file this question away as one of the more interesting philosophical problems you’ll explore in your next life.\n\nThe next life ",
        "source": "user",
        "start_progress": 0.3027166882276843,
        "end_progress": 0.3130659767141009,
        "start_time": 130.0,
        "end_time": 134.0,
        "last_event_time": 631.0,
        "residual_vector": 0.16229989754731755,
        "residual_vector_norm": 0.9980328560414942
    },
    {
        "sentence": "When you die, you appear in a cinema with a number of other people who look like you. You find out that they are your previous reincarnations, and soon you all begin watching your next life on the big screen. This next life is the most amazing one yet! You are rich, beautiful, and powerful. You are confused about the presence of your previous selves, but file this question away as one of the more interesting philosophical problems you’ll explore in your next life.\n\nThe next life is just as amazing as you expected it to be.",
        "source": "api",
        "start_progress": 0.3130659767141009,
        "end_progress": 0.34152652005174644,
        "start_time": 153.0,
        "end_time": 153.0,
        "last_event_time": 631.0,
        "residual_vector": 0.15934316001521348,
        "residual_vector_norm": 0.5505763822976423
    },
    {
        "sentence": "When you die, you appear in a cinema with a number of other people who look like you. You find out that they are your previous reincarnations, and soon you all begin watching your next life on the big screen. This next life is the most amazing one yet! You are rich, beautiful, and powerful. You are confused about the presence of your previous selves, but file this question away as one of the more interesting philosophical problems you’ll explore in your next life.\n\nThe next life is just as amazing as you expected it to be. You live in an amazing home. In this life you live alone and have a lot of freedom.",
        "source": "user",
        "start_progress": 0.34152652005174644,
        "end_progress": 0.3958602846054334,
        "start_time": 156.0,
        "end_time": 197.0,
        "last_event_time": 631.0,
        "residual_vector": 0.2171948476207846,
        "residual_vector_norm": 0.37742844946157833
    },
    {
        "sentence": "When you die, you appear in a cinema with a number of other people who look like you. You find out that they are your previous reincarnations, and soon you all begin watching your next life on the big screen. This next life is the most amazing one yet! You are rich, beautiful, and powerful. You are confused about the presence of your previous selves, but file this question away as one of the more interesting philosophical problems you’ll explore in your next life.\n\nThe next life is just as amazing as you expected it to be. You live in an amazing home. In this life you live alone and have a lot of freedom. There is no need to work as money comes in from investments.",
        "source": "api",
        "start_progress": 0.3958602846054334,
        "end_progress": 0.43531694695989653,
        "start_time": 240.0,
        "end_time": 240.0,
        "last_event_time": 631.0,
        "residual_vector": 0.14814126868994415,
        "residual_vector_norm": 0.35237240212806437
    },
    {
        "sentence": "When you die, you appear in a cinema with a number of other people who look like you. You find out that they are your previous reincarnations, and soon you all begin watching your next life on the big screen. This next life is the most amazing one yet! You are rich, beautiful, and powerful. You are confused about the presence of your previous selves, but file this question away as one of the more interesting philosophical problems you’ll explore in your next life.\n\nThe next life is just as amazing as you expected it to be. You live in an amazing home. In this life you live alone and have a lot of freedom. There is no need to work as money comes in from investments. You can spend you days how you choose.\n\nIn previous lives you knew people you wished you could help. You still think about them and it occurs to you how much even the smallest amount of resources can help them. ",
        "source": "user",
        "start_progress": 0.43531694695989653,
        "end_progress": 0.5724450194049159,
        "start_time": 263.0,
        "end_time": 323.0,
        "last_event_time": 631.0,
        "residual_vector": 0.2355042581565038,
        "residual_vector_norm": 0.17396784856184722
    },
    {
        "sentence": "When you die, you appear in a cinema with a number of other people who look like you. You find out that they are your previous reincarnations, and soon you all begin watching your next life on the big screen. This next life is the most amazing one yet! You are rich, beautiful, and powerful. You are confused about the presence of your previous selves, but file this question away as one of the more interesting philosophical problems you’ll explore in your next life.\n\nThe next life is just as amazing as you expected it to be. You live in an amazing home. In this life you live alone and have a lot of freedom. There is no need to work as money comes in from investments. You can spend you days how you choose.\n\nIn previous lives you knew people you wished you could help. You still think about them and it occurs to you how much even the smallest amount of resources can help them. You decide to help them in this life.",
        "source": "api",
        "start_progress": 0.5724450194049159,
        "end_progress": 0.5963777490297542,
        "start_time": 341.0,
        "end_time": 341.0,
        "last_event_time": 631.0,
        "residual_vector": 0.10627600717929668,
        "residual_vector_norm": 0.4244212345726359
    },
    {
        "sentence": "When you die, you appear in a cinema with a number of other people who look like you. You find out that they are your previous reincarnations, and soon you all begin watching your next life on the big screen. This next life is the most amazing one yet! You are rich, beautiful, and powerful. You are confused about the presence of your previous selves, but file this question away as one of the more interesting philosophical problems you’ll explore in your next life.\n\nThe next life is just as amazing as you expected it to be. You live in an amazing home. In this life you live alone and have a lot of freedom. There is no need to work as money comes in from investments. You can spend you days how you choose.\n\nIn previous lives you knew people you wished you could help. You still think about them and it occurs to you how much even the smallest amount of resources can help them. You decide to help them in this life. You have just enough money to give each of them $30,000 US dollars.",
        "source": "api",
        "start_progress": 0.5963777490297542,
        "end_progress": 0.6403622250970246,
        "start_time": 354.0,
        "end_time": 368.0,
        "last_event_time": 631.0,
        "residual_vector": 0.21195628051601367,
        "residual_vector_norm": 0.46541689575848344
    },
    {
        "sentence": "When you die, you appear in a cinema with a number of other people who look like you. You find out that they are your previous reincarnations, and soon you all begin watching your next life on the big screen. This next life is the most amazing one yet! You are rich, beautiful, and powerful. You are confused about the presence of your previous selves, but file this question away as one of the more interesting philosophical problems you’ll explore in your next life.\n\nThe next life is just as amazing as you expected it to be. You live in an amazing home. In this life you live alone and have a lot of freedom. There is no need to work as money comes in from investments. You can spend you days how you choose.\n\nIn previous lives you knew people you wished you could help. You still think about them and it occurs to you how much even the smallest amount of resources can help them. You decide to help them in this life. You have just enough money to give each of them $30,000 US dollars. The only thing to figure out is how to get the money to them.",
        "source": "user",
        "start_progress": 0.6403622250970246,
        "end_progress": 0.6804657179818887,
        "start_time": 372.0,
        "end_time": 388.0,
        "last_event_time": 631.0,
        "residual_vector": 0.08700340287784608,
        "residual_vector_norm": 0.20772604180062776
    },
    {
        "sentence": "When you die, you appear in a cinema with a number of other people who look like you. You find out that they are your previous reincarnations, and soon you all begin watching your next life on the big screen. This next life is the most amazing one yet! You are rich, beautiful, and powerful. You are confused about the presence of your previous selves, but file this question away as one of the more interesting philosophical problems you’ll explore in your next life.\n\nThe next life is just as amazing as you expected it to be. You live in an amazing home. In this life you live alone and have a lot of freedom. There is no need to work as money comes in from investments. You can spend you days how you choose.\n\nIn previous lives you knew people you wished you could help. You still think about them and it occurs to you how much even the smallest amount of resources can help them. You decide to help them in this life. You have just enough money to give each of them $30,000 US dollars. The only thing to figure out is how to get the money to them.\n\nYou remember seeing your previous selves and ",
        "source": "user",
        "start_progress": 0.6804657179818887,
        "end_progress": 0.7108667529107374,
        "start_time": 423.0,
        "end_time": 468.0,
        "last_event_time": 631.0,
        "residual_vector": 0.13027971322853615,
        "residual_vector_norm": 0.40780229190643547
    },
    {
        "sentence": "When you die, you appear in a cinema with a number of other people who look like you. You find out that they are your previous reincarnations, and soon you all begin watching your next life on the big screen. This next life is the most amazing one yet! You are rich, beautiful, and powerful. You are confused about the presence of your previous selves, but file this question away as one of the more interesting philosophical problems you’ll explore in your next life.\n\nThe next life is just as amazing as you expected it to be. You live in an amazing home. In this life you live alone and have a lot of freedom. There is no need to work as money comes in from investments. You can spend you days how you choose.\n\nIn previous lives you knew people you wished you could help. You still think about them and it occurs to you how much even the smallest amount of resources can help them. You decide to help them in this life. You have just enough money to give each of them $30,000 US dollars. The only thing to figure out is how to get the money to them.\n\nYou remember seeing your previous selves and think that they probably know how to get the money to the people you want to help.",
        "source": "api",
        "start_progress": 0.7108667529107374,
        "end_progress": 0.7639068564036222,
        "start_time": 478.0,
        "end_time": 478.0,
        "last_event_time": 631.0,
        "residual_vector": 0.12465160458890277,
        "residual_vector_norm": 0.2222294813543227
    },
    {
        "sentence": "When you die, you appear in a cinema with a number of other people who look like you. You find out that they are your previous reincarnations, and soon you all begin watching your next life on the big screen. This next life is the most amazing one yet! You are rich, beautiful, and powerful. You are confused about the presence of your previous selves, but file this question away as one of the more interesting philosophical problems you’ll explore in your next life.\n\nThe next life is just as amazing as you expected it to be. You live in an amazing home. In this life you live alone and have a lot of freedom. There is no need to work as money comes in from investments. You can spend you days how you choose.\n\nIn previous lives you knew people you wished you could help. You still think about them and it occurs to you how much even the smallest amount of resources can help them. You decide to help them in this life. You have just enough money to give each of them $30,000 US dollars. The only thing to figure out is how to get the money to them.\n\nYou remember seeing your previous selves and think that they probably know how to get the money to the people you want to help. You turn to them and say, “How do we get the money to these people?”",
        "source": "api",
        "start_progress": 0.7639068564036222,
        "end_progress": 0.8085381630012937,
        "start_time": 481.0,
        "end_time": 496.0,
        "last_event_time": 631.0,
        "residual_vector": 0.1251125473076401,
        "residual_vector_norm": 0.2610257208911993
    },
    {
        "sentence": "When you die, you appear in a cinema with a number of other people who look like you. You find out that they are your previous reincarnations, and soon you all begin watching your next life on the big screen. This next life is the most amazing one yet! You are rich, beautiful, and powerful. You are confused about the presence of your previous selves, but file this question away as one of the more interesting philosophical problems you’ll explore in your next life.\n\nThe next life is just as amazing as you expected it to be. You live in an amazing home. In this life you live alone and have a lot of freedom. There is no need to work as money comes in from investments. You can spend you days how you choose.\n\nIn previous lives you knew people you wished you could help. You still think about them and it occurs to you how much even the smallest amount of resources can help them. You decide to help them in this life. You have just enough money to give each of them $30,000 US dollars. The only thing to figure out is how to get the money to them.\n\nYou remember seeing your previous selves and think that they probably know how to get the money to the people you want to help. You turn to them and say, “How do we get the money to these people?” They tell you they must wait until the first of the year. ",
        "source": "user",
        "start_progress": 0.8085381630012937,
        "end_progress": 0.8467011642949547,
        "start_time": 539.0,
        "end_time": 552.0,
        "last_event_time": 631.0,
        "residual_vector": 0.19381361996834084,
        "residual_vector_norm": 0.4937958909905541
    },
    {
        "sentence": "When you die, you appear in a cinema with a number of other people who look like you. You find out that they are your previous reincarnations, and soon you all begin watching your next life on the big screen. This next life is the most amazing one yet! You are rich, beautiful, and powerful. You are confused about the presence of your previous selves, but file this question away as one of the more interesting philosophical problems you’ll explore in your next life.\n\nThe next life is just as amazing as you expected it to be. You live in an amazing home. In this life you live alone and have a lot of freedom. There is no need to work as money comes in from investments. You can spend you days how you choose.\n\nIn previous lives you knew people you wished you could help. You still think about them and it occurs to you how much even the smallest amount of resources can help them. You decide to help them in this life. You have just enough money to give each of them $30,000 US dollars. The only thing to figure out is how to get the money to them.\n\nYou remember seeing your previous selves and think that they probably know how to get the money to the people you want to help. You turn to them and say, “How do we get the money to these people?” They tell you they must wait until the first of the year. “That’s when the New Year’s money is given to them.”",
        "source": "api",
        "start_progress": 0.8467011642949547,
        "end_progress": 0.8803363518758085,
        "start_time": 563.0,
        "end_time": 563.0,
        "last_event_time": 631.0,
        "residual_vector": 0.11578389282455426,
        "residual_vector_norm": 0.32109271191981215
    },
    {
        "sentence": "When you die, you appear in a cinema with a number of other people who look like you. You find out that they are your previous reincarnations, and soon you all begin watching your next life on the big screen. This next life is the most amazing one yet! You are rich, beautiful, and powerful. You are confused about the presence of your previous selves, but file this question away as one of the more interesting philosophical problems you’ll explore in your next life.\n\nThe next life is just as amazing as you expected it to be. You live in an amazing home. In this life you live alone and have a lot of freedom. There is no need to work as money comes in from investments. You can spend you days how you choose.\n\nIn previous lives you knew people you wished you could help. You still think about them and it occurs to you how much even the smallest amount of resources can help them. You decide to help them in this life. You have just enough money to give each of them $30,000 US dollars. The only thing to figure out is how to get the money to them.\n\nYou remember seeing your previous selves and think that they probably know how to get the money to the people you want to help. You turn to them and say, “How do we get the money to these people?” They tell you they must wait until the first of the year. “That’s when the New Year’s money is given to them.” \n\nOn the first of the year you release the money to your prior selves and they deliver it to the people you wanted to have it. You and your prior selves then move on to your next life.",
        "source": "user",
        "start_progress": 0.8803363518758085,
        "end_progress": 1.0,
        "start_time": 570.0,
        "end_time": 631.0,
        "last_event_time": 631.0,
        "residual_vector": 0.1657528793920448,
        "residual_vector_norm": 0.15151629637848774
    }
]