[
    {
        "sentence": 0.6503333333333333,
        "source": "api",
        "start_progress": 0,
        "end_progress": 0.1435161455663762,
        "start_time": 0.0,
        "end_time": 0.0,
        "last_event_time": 718.0,
        "residual_vector": 0.0,
        "residual_vector_norm": 0,
        "score": 5
    },
    {
        "sentence": 0.6503333333333333,
        "source": "api",
        "start_progress": 0.1435161455663762,
        "end_progress": 0.176832393644285,
        "start_time": 19.0,
        "end_time": 32.0,
        "last_event_time": 718.0,
        "residual_vector": 0.2170529375235377,
        "residual_vector_norm": 0.5562101102084221,
        "score": 5
    },
    {
        "sentence": 0.6503333333333333,
        "source": "user",
        "start_progress": 0.176832393644285,
        "end_progress": 0.2347514095335725,
        "start_time": 35.0,
        "end_time": 81.0,
        "last_event_time": 718.0,
        "residual_vector": 0.38245366007013937,
        "residual_vector_norm": 0.6930060635878453,
        "score": 5
    },
    {
        "sentence": 0.6503333333333333,
        "source": "api",
        "start_progress": 0.2347514095335725,
        "end_progress": 0.25884161968221425,
        "start_time": 97.0,
        "end_time": 97.0,
        "last_event_time": 718.0,
        "residual_vector": 0.3902355126953805,
        "residual_vector_norm": 1.0,
        "score": 5
    },
    {
        "sentence": 0.6503333333333333,
        "source": "user",
        "start_progress": 0.25884161968221425,
        "end_progress": 0.40492055356227574,
        "start_time": 99.0,
        "end_time": 193.0,
        "last_event_time": 718.0,
        "residual_vector": 0.35579388297011433,
        "residual_vector_norm": 0.45587071319140626,
        "score": 5
    },
    {
        "sentence": 0.6503333333333333,
        "source": "user",
        "start_progress": 0.40492055356227574,
        "end_progress": 0.4325986673500769,
        "start_time": 196.0,
        "end_time": 216.0,
        "last_event_time": 718.0,
        "residual_vector": 0.1727609357569278,
        "residual_vector_norm": 0.44270941556204735,
        "score": 5
    },
    {
        "sentence": 0.6503333333333333,
        "source": "api",
        "start_progress": 0.4325986673500769,
        "end_progress": 0.44643772424397743,
        "start_time": 232.0,
        "end_time": 232.0,
        "last_event_time": 718.0,
        "residual_vector": 0.18803676743338052,
        "residual_vector_norm": 0.481854575803722,
        "score": 5
    },
    {
        "sentence": 0.6503333333333333,
        "source": "user",
        "start_progress": 0.44643772424397743,
        "end_progress": 0.46694003075345974,
        "start_time": 255.0,
        "end_time": 266.0,
        "last_event_time": 718.0,
        "residual_vector": 0.13204149548854094,
        "residual_vector_norm": 0.33836360657317494,
        "score": 5
    },
    {
        "sentence": 0.6503333333333333,
        "source": "api",
        "start_progress": 0.46694003075345974,
        "end_progress": 0.48898001025115323,
        "start_time": 275.0,
        "end_time": 275.0,
        "last_event_time": 718.0,
        "residual_vector": 0.17525619310799978,
        "residual_vector_norm": 0.4491036499920127,
        "score": 5
    },
    {
        "sentence": 0.6503333333333333,
        "source": "user",
        "start_progress": 0.48898001025115323,
        "end_progress": 0.5863659661711943,
        "start_time": 279.0,
        "end_time": 325.0,
        "last_event_time": 718.0,
        "residual_vector": 0.26293870476635156,
        "residual_vector_norm": 0.3890156765299994,
        "score": 5
    },
    {
        "sentence": 0.6503333333333333,
        "source": "api",
        "start_progress": 0.5863659661711943,
        "end_progress": 0.5981547924141466,
        "start_time": 336.0,
        "end_time": 336.0,
        "last_event_time": 718.0,
        "residual_vector": 0.1163313477119798,
        "residual_vector_norm": 0.29810548739778214,
        "score": 5
    },
    {
        "sentence": 0.6503333333333333,
        "source": "user",
        "start_progress": 0.5981547924141466,
        "end_progress": 0.7396207073295745,
        "start_time": 338.0,
        "end_time": 428.0,
        "last_event_time": 718.0,
        "residual_vector": 0.20404936545068053,
        "residual_vector_norm": 0.23384250641974946,
        "score": 5
    },
    {
        "sentence": 0.6503333333333333,
        "source": "api",
        "start_progress": 0.7396207073295745,
        "end_progress": 0.7688364941055869,
        "start_time": 448.0,
        "end_time": 450.0,
        "last_event_time": 718.0,
        "residual_vector": 0.13325282666817584,
        "residual_vector_norm": 0.34146770945522215,
        "score": 5
    },
    {
        "sentence": 0.6503333333333333,
        "source": "user",
        "start_progress": 0.7688364941055869,
        "end_progress": 0.8359815479241415,
        "start_time": 450.0,
        "end_time": 501.0,
        "last_event_time": 718.0,
        "residual_vector": 0.2979602297687006,
        "residual_vector_norm": 0.4408297381152171,
        "score": 5
    },
    {
        "sentence": 0.6503333333333333,
        "source": "api",
        "start_progress": 0.8359815479241415,
        "end_progress": 0.8928754484879549,
        "start_time": 516.0,
        "end_time": 516.0,
        "last_event_time": 718.0,
        "residual_vector": 0.18924602359624634,
        "residual_vector_norm": 0.4849533613409823,
        "score": 5
    },
    {
        "sentence": 0.6503333333333333,
        "source": "user",
        "start_progress": 0.8928754484879549,
        "end_progress": 1.0,
        "start_time": 523.0,
        "end_time": 718.0,
        "last_event_time": 718.0,
        "residual_vector": 0.1909962905617275,
        "residual_vector_norm": 0.244719258432561,
        "score": 5
    }
]